rye/__init__.py
rye/__main__.py
rye/application.py
rye/base_executable.py
rye/config.py
rye/default_config.py
rye/environment.py
rye/task.py
rye-0.6.1.dist-info/entry_points.txt
rye-0.6.1.dist-info/WHEEL
rye-0.6.1.dist-info/METADATA
rye-0.6.1.dist-info/RECORD
