Metadata-Version: 2.1
Name: rye
Version: 0.6.1
Summary: Concurrent and flexible task runner
Home-page: https://gitlab.com/pjbecotte/rye
License: MIT
Author: Paul Becotte
Author-email: pjbecotte@gmail.com
Requires-Python: >=3.6,<4.0
Classifier: License :: OSI Approved :: MIT License
Classifier: Programming Language :: Python :: 3
Classifier: Programming Language :: Python :: 3.6
Classifier: Programming Language :: Python :: 3.7
Classifier: Programming Language :: Python :: 3.8
Requires-Dist: click (>=7.0,<8.0)
Requires-Dist: colorama (>=0.4,<0.5)
Requires-Dist: importlib_metadata (>=0.23,<0.24)
Requires-Dist: pyyaml (>=5.1.2,<6.0.0)
Requires-Dist: settingscascade (>=0.5.0,<0.6.0)
Requires-Dist: toml (>=0.10,<0.11)
Requires-Dist: virtualenv (>=16.6,<17.0)
Project-URL: Repository, https://gitlab.com/pjbecotte/rye
